nppes/__init__.py
nppes/files.py
nppes/nppes_df.py
nppes/search.py
nppes-0.1.4.dist-info/entry_points.txt
nppes-0.1.4.dist-info/LICENSE
nppes-0.1.4.dist-info/WHEEL
nppes-0.1.4.dist-info/METADATA
nppes-0.1.4.dist-info/RECORD
